clearly/__init__.py
clearly/command_line.py
clearly/client/__init__.py
clearly/client/client.py
clearly/client/code_highlighter.py
clearly/client/display_modes.py
clearly/protos/__init__.py
clearly/protos/clearly_pb2.py
clearly/protos/clearly_pb2_grpc.py
clearly/server/__init__.py
clearly/server/event_listener.py
clearly/server/expected_state.py
clearly/server/server.py
clearly/server/streaming_dispatcher.py
clearly/utils/__init__.py
clearly/utils/colors.py
clearly/utils/data.py
clearly/utils/env_params.py
clearly/utils/logo.py
clearly/utils/safe_compiler.py
clearly/utils/worker_states.py
clearly-0.9.2.data/data/LICENSE
clearly-0.9.2.dist-info/LICENSE
clearly-0.9.2.dist-info/METADATA
clearly-0.9.2.dist-info/WHEEL
clearly-0.9.2.dist-info/entry_points.txt
clearly-0.9.2.dist-info/top_level.txt
clearly-0.9.2.dist-info/RECORD
