Metadata-Version: 2.1
Name: clearly
Version: 0.9.2
Summary: Clearly see and debug your celery cluster in real time!
Home-page: https://github.com/rsalmei/clearly
Author: Rogério Sampaio de Almeida
Author-email: rsalmei@gmail.com
License: MIT
Keywords: python,celery,distributed,task,queue,flower,monitor,monitoring-tool,asynchronous,real-time,realtime
Platform: UNKNOWN
Classifier: Development Status :: 4 - Beta
Classifier: Intended Audience :: Developers
Classifier: Environment :: Console
Classifier: Natural Language :: English
Classifier: Topic :: System :: Distributed Computing
Classifier: Topic :: System :: Monitoring
Classifier: License :: OSI Approved :: MIT License
Classifier: Programming Language :: Python :: 3
Classifier: Programming Language :: Python :: 3.6
Classifier: Programming Language :: Python :: 3.7
Classifier: Programming Language :: Python :: 3.8
Requires-Python: >=3.6, <4
Requires-Dist: celery[arangodb,cassandra,consul,dynamodb,elasticsearch,pymemcache,redis,riak,sqlalchemy] (>=3.1)
Requires-Dist: pygments
Requires-Dist: grpcio
Requires-Dist: protobuf
Requires-Dist: click
Requires-Dist: about-time (~=3.0)
Requires-Dist: ipython
Provides-Extra: ci
Requires-Dist: codecov ; extra == 'ci'
Requires-Dist: coveralls ; extra == 'ci'
Provides-Extra: dev
Requires-Dist: pdbpp ; extra == 'dev'
Requires-Dist: grpcio-tools ; extra == 'dev'
Requires-Dist: twine ; extra == 'dev'
Requires-Dist: wheel ; extra == 'dev'
Provides-Extra: test
Requires-Dist: pytest ; extra == 'test'
Requires-Dist: pytest-cov ; extra == 'test'
Requires-Dist: pytest-sugar ; extra == 'test'
Requires-Dist: pytest-watch ; extra == 'test'
